libwikit/__init__.py
libwikit/_version.py
libwikit/wikit.py
wikit-0.1.0.data/scripts/wikit
wikit-0.1.0.dist-info/METADATA
wikit-0.1.0.dist-info/WHEEL
wikit-0.1.0.dist-info/top_level.txt
wikit-0.1.0.dist-info/RECORD
